{"oms": {"fuente": "oms", "generado": "2026-06-18T21:28:48", "dias": {"2026-06-15": {"totales": {"ramplas": 4, "pallets": 83, "unidades": 22884}, "clientes": {"WM": {"ramplas": 3, "pallets": 74, "unidades": 22660, "sucursales": [{"sucursal": "20002563", "sala": "CD WM QUILICURA / 391", "ruta": "XSCL06", "manifiestos": [{"sufijo": "", "razon_social": "WALMART CHILE S.A", "citas": {"R1": "42464345 13:00", "R2": "42464350 16:00", "R3": "42464357 17:00"}, "ramplas": [{"id": "R1", "pallets": 28, "unidades": 8720, "cajas": 560, "cita": "42464345 13:00", "ocs": ["8250715093"], "articulos": [{"material": "100137", "desc": "MOLDE FAMILIAR INTEGRAL 630", "unidades": 400, "cajas": 40, "pallets_uso": 2, "oc": "8250715093"}, {"material": "100177", "desc": "PIZZA TRADICIONAL METRO", "unidades": 480, "cajas": 40, "pallets_uso": 2, "oc": "8250715093"}, {"material": "100140", "desc": "MOLDE INTEGRAL XL", "unidades": 600, "cajas": 100, "pallets_uso": 5, "oc": "8250715093"}, {"material": "100149", "desc": "PAN HAMBURGUESA", "unidades": 640, "cajas": 80, "pallets_uso": 4, "oc": "8250715093"}, {"material": "100150", "desc": "HAMBURGUESA 4", "unidades": 6600, "cajas": 300, "pallets_uso": 15, "oc": "8250715093"}], "key": "2026-06-15|CD WM QUILICURA / 391||R1"}, {"id": "R2", "pallets": 28, "unidades": 8540, "cajas": 560, "cita": "42464350 16:00", "ocs": ["8250715093"], "articulos": [{"material": "100150", "desc": "HAMBURGUESA 4", "unidades": 440, "cajas": 20, "pallets_uso": 1, "oc": "8250715093"}, {"material": "100146", "desc": "HOT DOG 5", "unidades": 8100, "cajas": 540, "pallets_uso": 27, "oc": "8250715093"}], "key": "2026-06-15|CD WM QUILICURA / 391||R2"}, {"id": "R3", "pallets": 18, "unidades": 5400, "cajas": 360, "cita": "42464357 17:00", "ocs": ["8250715093"], "articulos": [{"material": "100146", "desc": "HOT DOG 5", "unidades": 5400, "cajas": 360, "pallets_uso": 18, "oc": "8250715093"}], "key": "2026-06-15|CD WM QUILICURA / 391||R3"}]}]}]}, "SMU": {"ramplas": 1, "pallets": 9, "unidades": 224, "sucursales": [{"sucursal": "20002886", "sala": "CD UNI REFRIGERADO", "ruta": "ZCL013", "manifiestos": [{"sufijo": "", "razon_social": "RENDIC HERMANOS S.A.", "citas": {"R1": "cita: 182645692 , hora: 16:00 - 16:30 hrs"}, "ramplas": [{"id": "R1", "pallets": 9, "unidades": 224, "cajas": 26, "cita": "cita: 182645692 , hora: 16:00 - 16:30 hrs", "ocs": ["7000569117"], "articulos": [{"material": "100143", "desc": "MOLDE BLANCO XL", "unidades": 10, "cajas": 2, "pallets_uso": 1, "oc": "7000569117"}, {"material": "100140", "desc": "MOLDE INTEGRAL XL", "unidades": 10, "cajas": 2, "pallets_uso": 1, "oc": "7000569117"}, {"material": "100456", "desc": "MOLDE CAS LINAZA CHIA PREBIOT G&S 600G", "unidades": 18, "cajas": 2, "pallets_uso": 1, "oc": "7000569117"}, {"material": "100457", "desc": "MOLDE CAS MULTIGRANO PROTEINA G&S 620G", "unidades": 18, "cajas": 2, "pallets_uso": 1, "oc": "7000569117"}, {"material": "100177", "desc": "PIZZA TRADICIONAL METRO", "unidades": 24, "cajas": 2, "pallets_uso": 1, "oc": "7000569117"}, {"material": "100408", "desc": "PIERRE MOLDE INTEGRAL XL", "unidades": 30, "cajas": 5, "pallets_uso": 1, "oc": "7000569117"}, {"material": "100451", "desc": "MOLDE CAS LINAZA CHIA PREBIO T G&S 400G", "unidades": 36, "cajas": 2, "pallets_uso": 1, "oc": "7000569117"}, {"material": "100452", "desc": "MOLDE CAS MULTIGRANO PROTEINA G&S 400G", "unidades": 36, "cajas": 2, "pallets_uso": 1, "oc": "7000569117"}, {"material": "100407", "desc": "PIERRE MOLDE BLANCO XL", "unidades": 42, "cajas": 7, "pallets_uso": 1, "oc": "7000569117"}], "key": "2026-06-15|CD UNI REFRIGERADO||R1"}]}]}]}}}, "2026-06-16": {"totales": {"ramplas": 0, "pallets": 0, "unidades": 0}, "clientes": {}}, "2026-06-17": {"totales": {"ramplas": 0, "pallets": 0, "unidades": 0}, "clientes": {}}, "2026-06-18": {"totales": {"ramplas": 0, "pallets": 0, "unidades": 0}, "clientes": {}}, "2026-06-19": {"totales": {"ramplas": 8, "pallets": 221, "unidades": 40000}, "clientes": {"WM": {"ramplas": 8, "pallets": 221, "unidades": 40000, "sucursales": [{"sucursal": "20002563", "sala": "CD WM QUILICURA / 391", "ruta": "XSCL06", "manifiestos": [{"sufijo": "", "razon_social": "WALMART CHILE S.A", "citas": {"R1": "42469750 17:00", "R2": "42469812 17:00", "R3": "42469754 18:00", "R4": "42469763 16:00", "R5": "42469784 17:00", "R6": "42469790 17:00", "R7": "42469803 17:00", "R8": "42470833 17:00"}, "ramplas": [{"id": "R1", "pallets": 28, "unidades": 4120, "cajas": 560, "cita": "42469750 17:00", "ocs": ["8250715120"], "articulos": [{"material": "100137", "desc": "MOLDE FAMILIAR INTEGRAL 630", "unidades": 400, "cajas": 40, "pallets_uso": 2, "oc": "8250715120"}, {"material": "100143", "desc": "MOLDE BLANCO XL", "unidades": 600, "cajas": 100, "pallets_uso": 5, "oc": "8250715120"}, {"material": "100177", "desc": "PIZZA TRADICIONAL METRO", "unidades": 720, "cajas": 60, "pallets_uso": 3, "oc": "8250715120"}, {"material": "100149", "desc": "PAN HAMBURGUESA", "unidades": 960, "cajas": 120, "pallets_uso": 6, "oc": "8250715120"}, {"material": "100140", "desc": "MOLDE INTEGRAL XL", "unidades": 1440, "cajas": 240, "pallets_uso": 12, "oc": "8250715120"}], "key": "2026-06-19|CD WM QUILICURA / 391||R1"}, {"id": "R2", "pallets": 28, "unidades": 4640, "cajas": 560, "cita": "42469812 17:00", "ocs": ["8250715120"], "articulos": [{"material": "100402", "desc": "MOLDE INTEGRAL XL PROMOCIONAL", "unidades": 2880, "cajas": 480, "pallets_uso": 24, "oc": "8250715120"}, {"material": "100150", "desc": "HAMBURGUESA 4", "unidades": 1760, "cajas": 80, "pallets_uso": 4, "oc": "8250715120"}], "key": "2026-06-19|CD WM QUILICURA / 391||R2"}, {"id": "R3", "pallets": 28, "unidades": 9940, "cajas": 560, "cita": "42469754 18:00", "ocs": ["8250715120"], "articulos": [{"material": "100150", "desc": "HAMBURGUESA 4", "unidades": 4840, "cajas": 220, "pallets_uso": 11, "oc": "8250715120"}, {"material": "100146", "desc": "HOT DOG 5", "unidades": 5100, "cajas": 340, "pallets_uso": 17, "oc": "8250715120"}], "key": "2026-06-19|CD WM QUILICURA / 391||R3"}, {"id": "R4", "pallets": 28, "unidades": 8220, "cajas": 560, "cita": "42469763 16:00", "ocs": ["8250715120"], "articulos": [{"material": "100146", "desc": "HOT DOG 5", "unidades": 8100, "cajas": 540, "pallets_uso": 27, "oc": "8250715120"}, {"material": "100129", "desc": "MOLDE BLANCO XL PROMOCIONAL", "unidades": 120, "cajas": 20, "pallets_uso": 1, "oc": "8250715120"}], "key": "2026-06-19|CD WM QUILICURA / 391||R4"}, {"id": "R5", "pallets": 28, "unidades": 3360, "cajas": 560, "cita": "42469784 17:00", "ocs": ["8250715120"], "articulos": [{"material": "100129", "desc": "MOLDE BLANCO XL PROMOCIONAL", "unidades": 3360, "cajas": 560, "pallets_uso": 28, "oc": "8250715120"}], "key": "2026-06-19|CD WM QUILICURA / 391||R5"}, {"id": "R6", "pallets": 28, "unidades": 3360, "cajas": 560, "cita": "42469790 17:00", "ocs": ["8250715120"], "articulos": [{"material": "100129", "desc": "MOLDE BLANCO XL PROMOCIONAL", "unidades": 3360, "cajas": 560, "pallets_uso": 28, "oc": "8250715120"}], "key": "2026-06-19|CD WM QUILICURA / 391||R6"}, {"id": "R7", "pallets": 28, "unidades": 3360, "cajas": 560, "cita": "42469803 17:00", "ocs": ["8250715120"], "articulos": [{"material": "100129", "desc": "MOLDE BLANCO XL PROMOCIONAL", "unidades": 3360, "cajas": 560, "pallets_uso": 28, "oc": "8250715120"}], "key": "2026-06-19|CD WM QUILICURA / 391||R7"}, {"id": "R8", "pallets": 25, "unidades": 3000, "cajas": 500, "cita": "42470833 17:00", "ocs": ["8250715120"], "articulos": [{"material": "100129", "desc": "MOLDE BLANCO XL PROMOCIONAL", "unidades": 3000, "cajas": 500, "pallets_uso": 25, "oc": "8250715120"}], "key": "2026-06-19|CD WM QUILICURA / 391||R8"}]}]}]}}}, "2026-06-20": {"totales": {"ramplas": 0, "pallets": 0, "unidades": 0}, "clientes": {}}, "2026-06-21": {"totales": {"ramplas": 0, "pallets": 0, "unidades": 0}, "clientes": {}}, "2026-06-22": {"totales": {"ramplas": 6, "pallets": 145, "unidades": 27420}, "clientes": {"WM": {"ramplas": 6, "pallets": 145, "unidades": 27420, "sucursales": [{"sucursal": "20002563", "sala": "CD WM QUILICURA / 391", "ruta": "XSCL06", "manifiestos": [{"sufijo": "", "razon_social": "WALMART CHILE S.A", "citas": {"R1": "42478938 13:00", "R2": "42478940 15:00", "R3": "42478943 16:00", "R4": "42478944 16:00", "R5": "42478950 17:00", "R6": "42478952 17:00"}, "ramplas": [{"id": "R1", "pallets": 28, "unidades": 4040, "cajas": 560, "cita": "42478938 13:00", "ocs": ["8250715145"], "articulos": [{"material": "100137", "desc": "MOLDE FAMILIAR INTEGRAL 630", "unidades": 200, "cajas": 20, "pallets_uso": 1, "oc": "8250715145"}, {"material": "100177", "desc": "PIZZA TRADICIONAL METRO", "unidades": 720, "cajas": 60, "pallets_uso": 3, "oc": "8250715145"}, {"material": "100149", "desc": "PAN HAMBURGUESA", "unidades": 960, "cajas": 120, "pallets_uso": 6, "oc": "8250715145"}, {"material": "100140", "desc": "MOLDE INTEGRAL XL", "unidades": 1200, "cajas": 200, "pallets_uso": 10, "oc": "8250715145"}, {"material": "100143", "desc": "MOLDE BLANCO XL", "unidades": 960, "cajas": 160, "pallets_uso": 8, "oc": "8250715145"}], "key": "2026-06-22|CD WM QUILICURA / 391||R1"}, {"id": "R2", "pallets": 28, "unidades": 8380, "cajas": 560, "cita": "42478940 15:00", "ocs": ["8250715145"], "articulos": [{"material": "100143", "desc": "MOLDE BLANCO XL", "unidades": 1320, "cajas": 220, "pallets_uso": 11, "oc": "8250715145"}, {"material": "100150", "desc": "HAMBURGUESA 4", "unidades": 6160, "cajas": 280, "pallets_uso": 14, "oc": "8250715145"}, {"material": "100146", "desc": "HOT DOG 5", "unidades": 900, "cajas": 60, "pallets_uso": 3, "oc": "8250715145"}], "key": "2026-06-22|CD WM QUILICURA / 391||R2"}, {"id": "R3", "pallets": 28, "unidades": 7680, "cajas": 560, "cita": "42478943 16:00", "ocs": ["8250715145", "8250715154"], "articulos": [{"material": "100146", "desc": "HOT DOG 5", "unidades": 7200, "cajas": 480, "pallets_uso": 24, "oc": "8250715145"}, {"material": "100402", "desc": "MOLDE INTEGRAL XL PROMOCIONAL", "unidades": 480, "cajas": 80, "pallets_uso": 4, "oc": "8250715154"}], "key": "2026-06-22|CD WM QUILICURA / 391||R3"}, {"id": "R4", "pallets": 28, "unidades": 3360, "cajas": 560, "cita": "42478944 16:00", "ocs": ["8250715154"], "articulos": [{"material": "100402", "desc": "MOLDE INTEGRAL XL PROMOCIONAL", "unidades": 2160, "cajas": 360, "pallets_uso": 18, "oc": "8250715154"}, {"material": "100129", "desc": "MOLDE BLANCO XL PROMOCIONAL", "unidades": 1200, "cajas": 200, "pallets_uso": 10, "oc": "8250715154"}], "key": "2026-06-22|CD WM QUILICURA / 391||R4"}, {"id": "R5", "pallets": 28, "unidades": 3360, "cajas": 560, "cita": "42478950 17:00", "ocs": ["8250715154"], "articulos": [{"material": "100129", "desc": "MOLDE BLANCO XL PROMOCIONAL", "unidades": 3360, "cajas": 560, "pallets_uso": 28, "oc": "8250715154"}], "key": "2026-06-22|CD WM QUILICURA / 391||R5"}, {"id": "R6", "pallets": 5, "unidades": 600, "cajas": 100, "cita": "42478952 17:00", "ocs": ["8250715154"], "articulos": [{"material": "100129", "desc": "MOLDE BLANCO XL PROMOCIONAL", "unidades": 600, "cajas": 100, "pallets_uso": 5, "oc": "8250715154"}], "key": "2026-06-22|CD WM QUILICURA / 391||R6"}]}]}]}}}, "2026-06-23": {"totales": {"ramplas": 1, "pallets": 9, "unidades": 64}, "clientes": {"SMU": {"ramplas": 1, "pallets": 9, "unidades": 64, "sucursales": [{"sucursal": "20002886", "sala": "CD UNI REFRIGERADO", "ruta": "ZCL013", "manifiestos": [{"sufijo": "", "razon_social": "RENDIC HERMANOS S.A.", "citas": {"R1": ""}, "ramplas": [{"id": "R1", "pallets": 9, "unidades": 64, "cajas": 10, "cita": "", "ocs": ["7000569662", "7000569879"], "articulos": [{"material": "100140", "desc": "MOLDE INTEGRAL XL", "unidades": 5, "cajas": 1, "pallets_uso": 1, "oc": "7000569662"}, {"material": "100407", "desc": "PIERRE MOLDE BLANCO XL", "unidades": 6, "cajas": 1, "pallets_uso": 1, "oc": "7000569662"}, {"material": "100408", "desc": "PIERRE MOLDE INTEGRAL XL", "unidades": 6, "cajas": 1, "pallets_uso": 1, "oc": "7000569662"}, {"material": "100456", "desc": "MOLDE CAS LINAZA CHIA PREBIOT G&S 600G", "unidades": 6, "cajas": 1, "pallets_uso": 1, "oc": "7000569662"}, {"material": "100457", "desc": "MOLDE CAS MULTIGRANO PROTEINA G&S 620G", "unidades": 6, "cajas": 1, "pallets_uso": 1, "oc": "7000569662"}, {"material": "100140", "desc": "MOLDE INTEGRAL XL", "unidades": 5, "cajas": 1, "pallets_uso": 1, "oc": "7000569879"}, {"material": "100408", "desc": "PIERRE MOLDE INTEGRAL XL", "unidades": 6, "cajas": 1, "pallets_uso": 1, "oc": "7000569879"}, {"material": "100177", "desc": "PIZZA TRADICIONAL METRO", "unidades": 12, "cajas": 1, "pallets_uso": 1, "oc": "7000569879"}, {"material": "100407", "desc": "PIERRE MOLDE BLANCO XL", "unidades": 12, "cajas": 2, "pallets_uso": 1, "oc": "7000569879"}], "key": "2026-06-23|CD UNI REFRIGERADO||R1"}]}]}]}}}, "2026-06-24": {"totales": {"ramplas": 0, "pallets": 0, "unidades": 0}, "clientes": {}}, "2026-06-25": {"totales": {"ramplas": 0, "pallets": 0, "unidades": 0}, "clientes": {}}, "2026-06-26": {"totales": {"ramplas": 0, "pallets": 0, "unidades": 0}, "clientes": {}}, "2026-06-27": {"totales": {"ramplas": 0, "pallets": 0, "unidades": 0}, "clientes": {}}, "2026-06-28": {"totales": {"ramplas": 0, "pallets": 0, "unidades": 0}, "clientes": {}}}}, "carpetas": {"fuente": "carpetas", "generado": "2026-06-18T21:27:11", "dias": {"2026-06-22": {"totales": {"ramplas": 6, "pallets": 145, "unidades": 27420}, "clientes": {"WM": {"ramplas": 6, "pallets": 145, "unidades": 27420, "sucursales": [{"sucursal": "20002563", "sala": "CD WM QUILICURA / 391", "ruta": "XSCL06", "manifiestos": [{"sufijo": "", "razon_social": "", "citas": {"R1": "42478938 13:00", "R2": "42478940 15:00", "R3": "42478943 16:00", "R4": "42478944 16:00", "R5": "42478950 17:00", "R6": "42478952 17:00"}, "ramplas": [{"id": "R1", "pallets": 28, "unidades": 4040, "cajas": 560, "cita": "42478938 13:00", "ocs": ["8250715145"], "articulos": [{"material": "100137", "desc": "", "unidades": 200, "cajas": 20, "pallets_uso": 1, "oc": "8250715145"}, {"material": "100177", "desc": "", "unidades": 720, "cajas": 60, "pallets_uso": 3, "oc": "8250715145"}, {"material": "100149", "desc": "", "unidades": 960, "cajas": 120, "pallets_uso": 6, "oc": "8250715145"}, {"material": "100140", "desc": "", "unidades": 1200, "cajas": 200, "pallets_uso": 10, "oc": "8250715145"}, {"material": "100143", "desc": "", "unidades": 960, "cajas": 160, "pallets_uso": 8, "oc": "8250715145"}], "key": "2026-06-22|CD WM QUILICURA / 391||R1"}, {"id": "R2", "pallets": 28, "unidades": 8380, "cajas": 560, "cita": "42478940 15:00", "ocs": ["8250715145"], "articulos": [{"material": "100143", "desc": "", "unidades": 1320, "cajas": 220, "pallets_uso": 11, "oc": "8250715145"}, {"material": "100150", "desc": "", "unidades": 6160, "cajas": 280, "pallets_uso": 14, "oc": "8250715145"}, {"material": "100146", "desc": "", "unidades": 900, "cajas": 60, "pallets_uso": 3, "oc": "8250715145"}], "key": "2026-06-22|CD WM QUILICURA / 391||R2"}, {"id": "R3", "pallets": 28, "unidades": 7680, "cajas": 560, "cita": "42478943 16:00", "ocs": ["8250715145", "8250715154"], "articulos": [{"material": "100146", "desc": "", "unidades": 7200, "cajas": 480, "pallets_uso": 24, "oc": "8250715145"}, {"material": "100402", "desc": "", "unidades": 480, "cajas": 80, "pallets_uso": 4, "oc": "8250715154"}], "key": "2026-06-22|CD WM QUILICURA / 391||R3"}, {"id": "R4", "pallets": 28, "unidades": 3360, "cajas": 560, "cita": "42478944 16:00", "ocs": ["8250715154"], "articulos": [{"material": "100402", "desc": "", "unidades": 2160, "cajas": 360, "pallets_uso": 18, "oc": "8250715154"}, {"material": "100129", "desc": "", "unidades": 1200, "cajas": 200, "pallets_uso": 10, "oc": "8250715154"}], "key": "2026-06-22|CD WM QUILICURA / 391||R4"}, {"id": "R5", "pallets": 28, "unidades": 3360, "cajas": 560, "cita": "42478950 17:00", "ocs": ["8250715154"], "articulos": [{"material": "100129", "desc": "", "unidades": 3360, "cajas": 560, "pallets_uso": 28, "oc": "8250715154"}], "key": "2026-06-22|CD WM QUILICURA / 391||R5"}, {"id": "R6", "pallets": 5, "unidades": 600, "cajas": 100, "cita": "42478952 17:00", "ocs": ["8250715154"], "articulos": [{"material": "100129", "desc": "", "unidades": 600, "cajas": 100, "pallets_uso": 5, "oc": "8250715154"}], "key": "2026-06-22|CD WM QUILICURA / 391||R6"}]}]}]}}}}}, "sap": {"fuente": "sap", "generado": "2026-06-18T21:27:11", "dias": {"2026-06-22": {"totales": {"ramplas": 6, "pallets": 145, "unidades": 27420}, "clientes": {"WM": {"ramplas": 6, "pallets": 145, "unidades": 27420, "sucursales": [{"sucursal": "20002563", "sala": "CD WM QUILICURA / 391", "ruta": "XSCL06", "manifiestos": [{"sufijo": "", "razon_social": "", "citas": {"R1": "42478938 13:00", "R2": "42478940 15:00", "R3": "42478943 16:00", "R4": "42478944 16:00", "R5": "42478950 17:00", "R6": "42478952 17:00"}, "ramplas": [{"id": "R1", "estado": "CARGADA", "notas_sap": ["200589090"], "mensajes": ["Pedido creado: 200589090 8250715145"], "pallets": 28, "unidades": 4040, "cajas": 0, "cita": "42478938 13:00", "ocs": ["8250715145"], "articulos": [], "key": "2026-06-22|CD WM QUILICURA / 391||R1"}, {"id": "R2", "estado": "CARGADA", "notas_sap": ["200589091"], "mensajes": ["Pedido creado: 200589091 8250715145"], "pallets": 28, "unidades": 8380, "cajas": 0, "cita": "42478940 15:00", "ocs": ["8250715145"], "articulos": [], "key": "2026-06-22|CD WM QUILICURA / 391||R2"}, {"id": "R3", "estado": "CARGADA", "notas_sap": ["200589092", "200589093"], "mensajes": ["Pedido creado: 200589092 8250715145", "Pedido creado: 200589093 8250715154"], "pallets": 28, "unidades": 7680, "cajas": 0, "cita": "42478943 16:00", "ocs": ["8250715145", "8250715154"], "articulos": [], "key": "2026-06-22|CD WM QUILICURA / 391||R3"}, {"id": "R4", "estado": "CARGADA", "notas_sap": ["200589094"], "mensajes": ["Pedido creado: 200589094 8250715154"], "pallets": 28, "unidades": 3360, "cajas": 0, "cita": "42478944 16:00", "ocs": ["8250715154"], "articulos": [], "key": "2026-06-22|CD WM QUILICURA / 391||R4"}, {"id": "R5", "estado": "CARGADA", "notas_sap": ["200589095"], "mensajes": ["Pedido creado: 200589095 8250715154"], "pallets": 28, "unidades": 3360, "cajas": 0, "cita": "42478950 17:00", "ocs": ["8250715154"], "articulos": [], "key": "2026-06-22|CD WM QUILICURA / 391||R5"}, {"id": "R6", "estado": "CARGADA", "notas_sap": ["200589096"], "mensajes": ["Pedido creado: 200589096 8250715154"], "pallets": 5, "unidades": 600, "cajas": 0, "cita": "42478952 17:00", "ocs": ["8250715154"], "articulos": [], "key": "2026-06-22|CD WM QUILICURA / 391||R6"}]}]}]}}}}}, "observaciones": {"clientes": {"WM": {"KAM": "Jose Postigo Gonzalez", "KAM_mail": "jose.postigo@castano.cl", "CPFR": "Stephanie Gonzalez Paredes", "CPFR_mail": "stephanie.gonzalez@castano.cl"}, "CENCO": {"KAM": "Boris Fernandez", "KAM_mail": "boris.fernandez@castano.cl", "CPFR": "Diego Gonzalez Figueroa", "CPFR_mail": "diego.gonzalez@castano.cl"}, "SMU": {"KAM": "Guillermo Riveros Grebe", "KAM_mail": "guillermo.riveros@castano.cl", "CPFR": "Daniela Sanchez", "CPFR_mail": "daniela.sanchez@castano.cl"}, "TOTTUS": {"KAM": "Guillermo Riveros Grebe", "KAM_mail": "guillermo.riveros@castano.cl", "CPFR": "Natalia Faundez Ramos", "CPFR_mail": "natalia.faundez@castano.cl"}}, "ramplas": {}}, "config": {"capacidad_dia": 22, "titulo": "Monitor de Planificacion de Picking - Centralizado"}, "meta": {"hoy": "2026-07-14", "fechas": ["2026-07-13", "2026-07-14", "2026-07-15", "2026-07-16", "2026-07-17", "2026-07-18", "2026-07-19", "2026-07-20", "2026-07-21", "2026-07-22", "2026-07-23", "2026-07-24", "2026-07-25", "2026-07-26"], "semanas": [{"iso": "2026-W29", "num": 29, "anio": 2026, "inicio": "2026-07-13", "fin": "2026-07-19", "dias": ["2026-07-13", "2026-07-14", "2026-07-15", "2026-07-16", "2026-07-17", "2026-07-18", "2026-07-19"]}, {"iso": "2026-W30", "num": 30, "anio": 2026, "inicio": "2026-07-20", "fin": "2026-07-26", "dias": ["2026-07-20", "2026-07-21", "2026-07-22", "2026-07-23", "2026-07-24", "2026-07-25", "2026-07-26"]}], "dias_nombres": ["Lunes", "Martes", "Miércoles", "Jueves", "Viernes", "Sábado", "Domingo"]}, "publicado": "2026-07-14T15:19:08"}